Metadata-Version: 2.1
Name: mycrypto
Version: 1.3
Summary: A common cryptography encryption and decryption tools
Home-page: https://github.com/nightRainy/my_crypto
Author: ZhiShi
Author-email: foxfoxfox940@foxmail.com
License: MIT
Platform: UNKNOWN
